streamlit_image_select/__init__.py
streamlit_image_select/frontend/build/asset-manifest.json
streamlit_image_select/frontend/build/index.html
streamlit_image_select/frontend/build/precache-manifest.153d0c316dba828e107bbdaf23089584.js
streamlit_image_select/frontend/build/precache-manifest.52387f669f0e255c9428f1567c095b78.js
streamlit_image_select/frontend/build/precache-manifest.c89c98073d7d5874354feb7b56551ad9.js
streamlit_image_select/frontend/build/precache-manifest.f11cf7994886a9d920b7e49d4397e211.js
streamlit_image_select/frontend/build/service-worker.js
streamlit_image_select/frontend/build/styles.css
streamlit_image_select/frontend/build/static/js/2.5d2a6afa.chunk.js
streamlit_image_select/frontend/build/static/js/2.5d2a6afa.chunk.js.LICENSE.txt
streamlit_image_select/frontend/build/static/js/2.5d2a6afa.chunk.js.map
streamlit_image_select/frontend/build/static/js/2.aa1b5e8a.chunk.js
streamlit_image_select/frontend/build/static/js/2.aa1b5e8a.chunk.js.LICENSE.txt
streamlit_image_select/frontend/build/static/js/2.aa1b5e8a.chunk.js.map
streamlit_image_select/frontend/build/static/js/main.3a4cfc3a.chunk.js
streamlit_image_select/frontend/build/static/js/main.3a4cfc3a.chunk.js.map
streamlit_image_select/frontend/build/static/js/main.7a9075cc.chunk.js
streamlit_image_select/frontend/build/static/js/main.7a9075cc.chunk.js.map
streamlit_image_select/frontend/build/static/js/main.93e9e991.chunk.js
streamlit_image_select/frontend/build/static/js/main.93e9e991.chunk.js.map
streamlit_image_select/frontend/build/static/js/main.df56299e.chunk.js
streamlit_image_select/frontend/build/static/js/main.df56299e.chunk.js.map
streamlit_image_select/frontend/build/static/js/runtime-main.fce4c018.js
streamlit_image_select/frontend/build/static/js/runtime-main.fce4c018.js.map
streamlit_image_select_rows-0.8.dist-info/licenses/LICENSE
streamlit_image_select_rows-0.8.dist-info/METADATA
streamlit_image_select_rows-0.8.dist-info/WHEEL
streamlit_image_select_rows-0.8.dist-info/top_level.txt
streamlit_image_select_rows-0.8.dist-info/RECORD
