Metadata-Version: 2.4
Name: streamlit-image-select-rows
Version: 0.8
Summary: 🖼️ An image select component for Streamlit
License: MIT
Requires-Python: >=3.6
License-File: LICENSE
Requires-Dist: streamlit>=0.63
Dynamic: description
Dynamic: description-content-type
Dynamic: license
Dynamic: license-file
Dynamic: requires-dist
Dynamic: requires-python
Dynamic: summary
